coreshub_mcp_server/__init__.py
coreshub_mcp_server/__main__.py
coreshub_mcp_server/base_plugin.py
coreshub_mcp_server/server.py
coreshub_mcp_server/settings.py
coreshub_mcp_server/plugins/Inference_service.py
coreshub_mcp_server/plugins/__init__.py
coreshub_mcp_server/plugins/container_notebooks.py
coreshub_mcp_server/plugins/distributed_training.py
coreshub_mcp_server/plugins/epfs_filesystem.py
coreshub_mcp_server/plugins/example.py
coreshub_mcp_server/utils/__init__.py
coreshub_mcp_server/utils/signature.py
coreshub_mcp_server-0.2.0.dist-info/METADATA
coreshub_mcp_server-0.2.0.dist-info/WHEEL
coreshub_mcp_server-0.2.0.dist-info/entry_points.txt
coreshub_mcp_server-0.2.0.dist-info/RECORD
