Metadata-Version: 2.4
Name: coreshub-mcp-server
Version: 0.2.0
Summary: A lightweight mcp server for coreshub.
Author: eddic
Maintainer: eddic
License: MIT
Keywords: extensible,llm,mcp,plugin
Classifier: Development Status :: 4 - Beta
Classifier: Intended Audience :: Developers
Classifier: License :: OSI Approved :: MIT License
Classifier: Programming Language :: Python :: 3
Classifier: Programming Language :: Python :: 3.10
Requires-Python: >=3.10
Requires-Dist: mcp==1.6.0
Requires-Dist: pydantic-settings==2.9.1
Requires-Dist: pydantic==2.11.3
Requires-Dist: requests==2.32.3
